{"errors":[],"warnings":[],"namedChunkGroups":{"app":{"chunks":[6,0,2],"assets":["webpack-runtime-61142705697b1b608b26.js","webpack-runtime-61142705697b1b608b26.js.map","commons-cc051047d162e7351cdf.js","commons-cc051047d162e7351cdf.js.map","app-b1262bbd5ce4afcb17ea.js","app-b1262bbd5ce4afcb17ea.js.map"],"children":{},"childAssets":{}},"component---src-pages-404-js":{"chunks":[1,0,3],"assets":["styles.d5ef0abb16ee382cea7f.css","styles-46e0e26cf4fc3c90315b.js","styles-46e0e26cf4fc3c90315b.js.map","commons-cc051047d162e7351cdf.js","commons-cc051047d162e7351cdf.js.map","component---src-pages-404-js-0290f163286959b63491.js","component---src-pages-404-js-0290f163286959b63491.js.map"],"children":{},"childAssets":{}},"component---src-pages-index-js":{"chunks":[1,0,4],"assets":["styles.d5ef0abb16ee382cea7f.css","styles-46e0e26cf4fc3c90315b.js","styles-46e0e26cf4fc3c90315b.js.map","commons-cc051047d162e7351cdf.js","commons-cc051047d162e7351cdf.js.map","component---src-pages-index-js-5caa7ea04109006ef8ca.js","component---src-pages-index-js-5caa7ea04109006ef8ca.js.map"],"children":{},"childAssets":{}},"component---src-pages-page-2-js":{"chunks":[1,0,5],"assets":["styles.d5ef0abb16ee382cea7f.css","styles-46e0e26cf4fc3c90315b.js","styles-46e0e26cf4fc3c90315b.js.map","commons-cc051047d162e7351cdf.js","commons-cc051047d162e7351cdf.js.map","component---src-pages-page-2-js-c533758acaabdefda86a.js","component---src-pages-page-2-js-c533758acaabdefda86a.js.map"],"children":{},"childAssets":{}}},"assetsByChunkName":{"app":["webpack-runtime-61142705697b1b608b26.js","commons-cc051047d162e7351cdf.js","app-b1262bbd5ce4afcb17ea.js"],"component---src-pages-404-js":["styles.d5ef0abb16ee382cea7f.css","styles-46e0e26cf4fc3c90315b.js","commons-cc051047d162e7351cdf.js","component---src-pages-404-js-0290f163286959b63491.js"],"component---src-pages-index-js":["styles.d5ef0abb16ee382cea7f.css","styles-46e0e26cf4fc3c90315b.js","commons-cc051047d162e7351cdf.js","component---src-pages-index-js-5caa7ea04109006ef8ca.js"],"component---src-pages-page-2-js":["styles.d5ef0abb16ee382cea7f.css","styles-46e0e26cf4fc3c90315b.js","commons-cc051047d162e7351cdf.js","component---src-pages-page-2-js-c533758acaabdefda86a.js"]}}